starburst_client/__init__.py
starburst_client/_version.py
starburst_client/auth.py
starburst_client/client.py
starburst_client/exceptions.py
starburst_client/model.py
starburst_client/starburst.py
starburst_client-0.1.0.dist-info/LICENSE
starburst_client-0.1.0.dist-info/METADATA
starburst_client-0.1.0.dist-info/WHEEL
starburst_client-0.1.0.dist-info/top_level.txt
starburst_client-0.1.0.dist-info/RECORD
